LICENSE.txt
MANIFEST.in
README.rst
setup.py
neat/__init__.py
neat/__version__.py
neat/channels/__init__.py
neat/channels/compilechannels
neat/channels/concmechs.py
neat/channels/ionchannels.py
neat/channels/writecppcode.py
neat/channels/writemodfiles.py
neat/channels/channelcollection/__init__.py
neat/channels/channelcollection/channelcollection.py
neat/tools/__init__.py
neat/tools/kernelextraction.py
neat/tools/fittools/__init__.py
neat/tools/fittools/compartmentfitter.py
neat/tools/fittools/histogramsegmentation.py
neat/tools/fittools/iepsolver.py
neat/tools/fittools/zerofinding.py
neat/tools/plottools/__init__.py
neat/tools/plottools/scalebars.py
neat/tools/simtools/net/Ionchannels.cc
neat/tools/simtools/net/NETC.cc
neat/tools/simtools/net/Synapses.cc
neat/tools/simtools/net/Tools.cc
neat/tools/simtools/net/netsim.pyx
neat/tools/simtools/neuron/__init__.py
neat/tools/simtools/neuron/neuronmodel.py
neat/tools/simtools/neuron/mech_storage/CaDyn.mod
neat/tools/simtools/neuron/mech_storage/CaPump.mod
neat/tools/simtools/neuron/mech_storage/NMDA_Mg_T.mod
neat/tools/simtools/neuron/mech_storage/OUClamp.mod
neat/tools/simtools/neuron/mech_storage/OUClamp2.mod
neat/tools/simtools/neuron/mech_storage/OUConductance.mod
neat/tools/simtools/neuron/mech_storage/OUReversal.mod
neat/tools/simtools/neuron/mech_storage/Shunt.mod
neat/tools/simtools/neuron/mech_storage/SinClamp.mod
neat/tools/simtools/neuron/mech_storage/VecStim.mod
neat/tools/simtools/neuron/mech_storage/WNClamp.mod
neat/tools/simtools/neuron/mech_storage/conc_ca.mod
neat/tools/simtools/neuron/mech_storage/conc_ca_.mod
neat/tools/simtools/neuron/mech_storage/conc_ca__.mod
neat/tools/simtools/neuron/mech_storage/double_exp_AMPA_NMDA.mod
neat/tools/simtools/neuron/mech_storage/double_exp_AMPA_NMDA_modified.mod
neat/tools/simtools/neuron/mech_storage/double_exp_AMPA_NMDA_modified2.mod
neat/tools/simtools/neuron/mech_storage/double_exp_AMPA_NMDA_rescaled.mod
neatdend.egg-info/PKG-INFO
neatdend.egg-info/SOURCES.txt
neatdend.egg-info/dependency_links.txt
neatdend.egg-info/requires.txt
neatdend.egg-info/top_level.txt