Metadata-Version: 2.1
Name: neatdend
Version: 0.9.1
Summary: UNKNOWN
Home-page: https://github.com/unibe-cns/NEAT
Author: Willem Wybo, Jakob Jordan, Benjamin Ellenberger
License: GPLv3
Platform: UNKNOWN
Classifier: Development Status :: 3 - Alpha
Classifier: Programming Language :: Python :: 3.7
Classifier: License :: OSI Approved :: GNU General Public License v3 (GPLv3)
License-File: LICENSE.txt
